{
    "sync_product": {
        "name": "Clear Case for Samsung®"
    },
    "sync_variants": [
        {
            "variant_id": 9945,
            "files": [
                {
                    "url": "https://files.cdn.printful.com/products/267/9945_1582201424.jpg"
                }
            ]
        },
        {
            "variant_id": 9947,
            "files": [
                {
                    "url": "https://files.cdn.printful.com/products/267/9947_1582201447.jpg"
                }
            ]
        },
        {
            "variant_id": 9946,
            "files": [
                {
                    "url": "https://files.cdn.printful.com/products/267/9946_1582201474.jpg"
                }
            ]
        },
        {
            "variant_id": 12024,
            "files": [
                {
                    "url": "https://files.cdn.printful.com/products/267/12024_1614239810.jpg"
                }
            ]
        },
        {
            "variant_id": 11348,
            "files": [
                {
                    "url": "https://files.cdn.printful.com/products/267/11348_1584528498.jpg"
                }
            ]
        },
        {
            "variant_id": 11349,
            "files": [
                {
                    "url": "https://files.cdn.printful.com/products/267/11349_1584528399.jpg"
                }
            ]
        },
        {
            "variant_id": 11347,
            "files": [
                {
                    "url": "https://files.cdn.printful.com/products/267/11347_1584528512.jpg"
                }
            ]
        },
        {
            "variant_id": 12027,
            "files": [
                {
                    "url": "https://files.cdn.printful.com/products/267/12027_1615296293.jpg"
                }
            ]
        },
        {
            "variant_id": 12026,
            "files": [
                {
                    "url": "https://files.cdn.printful.com/products/267/12026_1615296332.jpg"
                }
            ]
        },
        {
            "variant_id": 12025,
            "files": [
                {
                    "url": "https://files.cdn.printful.com/products/267/12025_1615296198.jpg"
                }
            ]
        },
        {
            "variant_id": 14634,
            "files": [
                {
                    "url": "https://files.cdn.printful.com/products/267/14634_1645797547.jpg"
                }
            ]
        },
        {
            "variant_id": 14635,
            "files": [
                {
                    "url": "https://files.cdn.printful.com/products/267/14635_1645797548.jpg"
                }
            ]
        },
        {
            "variant_id": 14633,
            "files": [
                {
                    "url": "https://files.cdn.printful.com/products/267/14633_1645797555.jpg"
                }
            ]
        }
    ]
}